archive/adafruit_ble_discover.py
archive/discover.py
archive/setup.py
examples/ble/analog_input_ble.py
examples/ble/blink_ble.py
examples/ble/dac_ble.py
examples/ble/dht_ble.py
examples/ble/digital_input_ble.py
examples/ble/digital_input_pulldown_ble.py
examples/ble/digital_input_pullup_ble.py
examples/ble/fade_ble.py
examples/ble/hc-sr04_distance_sensor_ble.py
examples/ble/i2c_adxl345_accelerometer_ble.py
examples/ble/loop_back_ble.py
examples/ble/onewire_ds18x20_ble.py
examples/ble/servo_ble.py
examples/ble/spi_mpu9250_ble.py
examples/ble/stepper_absolute_ble.py
examples/ble/stepper_continuous_ble.py
examples/ble/stepper_relative_ble.py
examples/ble/touch_input_ble.py
examples/ble-aio/analog_input_ble_aio.py
examples/ble-aio/blink_ble_aio.py
examples/ble-aio/dac_ble_aio.py
examples/ble-aio/dht_ble_aio.py
examples/ble-aio/digital_input_ble_aio.py
examples/ble-aio/digital_input_pulldown_ble_aio.py
examples/ble-aio/digital_input_pullup_ble_aio.py
examples/ble-aio/fade_ble_aio.py
examples/ble-aio/hc-sr04_distance_sensor_ble_aio.py
examples/ble-aio/i2c_adxl345_accelerometer_ble_aio.py
examples/ble-aio/loop_back_ble_aio.py
examples/ble-aio/onewire_ds18x20_ble_aio.py
examples/ble-aio/servo_ble_aio.py
examples/ble-aio/spi_mpu9250_ble_aio.py
examples/ble-aio/stepper_absolute_ble_aio.py
examples/ble-aio/stepper_continuous_ble_aio.py
examples/ble-aio/stepper_relative_ble_aio.py
examples/ble-aio/touch_input_ble_aio.py
examples/wifi/analog_input_wifi.py
examples/wifi/blink_wifi.py
examples/wifi/dac_wifi.py
examples/wifi/dht_wifi.py
examples/wifi/digital_input_pulldown_wifi.py
examples/wifi/digital_input_pullup_wifi.py
examples/wifi/digital_input_wifi.py
examples/wifi/fade_wifi.py
examples/wifi/hc-sr04_distance_sensor_wifi.py
examples/wifi/i2c_adxl345_accelerometer_wifi.py
examples/wifi/loop_back_wifi.py
examples/wifi/onewire_ds18x20_wifi.py
examples/wifi/servo_wifi.py
examples/wifi/spi_mpu9250_wifi.py
examples/wifi/stepper_absolute_wifi.py
telemetrix_esp32-2.0.0.dist-info/METADATA
telemetrix_esp32-2.0.0.dist-info/WHEEL
telemetrix_esp32-2.0.0.dist-info/top_level.txt
telemetrix_esp32-2.0.0.dist-info/RECORD
