Metadata-Version: 2.1
Name: telemetrix-esp32
Version: 2.0.0
Summary: Telemetrix Client For The ESP32
Author-email: Alan Yorinks <MisterYsLab@gmail.com>
License: AGPL-3.0-or-later
Keywords: telemetrix,ESP32,Python
Classifier: Development Status :: 5 - Production/Stable
Classifier: Environment :: Other Environment
Classifier: Intended Audience :: Developers
Classifier: Intended Audience :: Education
Classifier: Operating System :: OS Independent
Classifier: Topic :: Software Development :: Libraries :: Python Modules
Requires-Python: >=3.8
Requires-Dist: pyserial
Requires-Dist: bleak
Requires-Dist: adafruit-blinka-bleio
Requires-Dist: adafruit-circuitpython-ble
